capebase/__init__.py
capebase/api.py
capebase/audit.py
capebase/database.py
capebase/exceptions.py
capebase/main.py
capebase/models.py
capebase/notification.py
capebase/py.typed
capebase/test.py
capebase/turbo_streams.py
capebase/types.py
capebase/utils.py
capebase/auth/__init__.py
capebase/auth/access_control.py
capebase/auth/row_level_security.py
capebase/auth/security.py
capebase-0.1.0a3.dist-info/METADATA
capebase-0.1.0a3.dist-info/WHEEL
capebase-0.1.0a3.dist-info/licenses/LICENSE
capebase-0.1.0a3.dist-info/RECORD
