Metadata-Version: 2.4
Name: capebase
Version: 0.1.0a3
Summary: A Python library for building real-time backends with auto-generated APIs, real-time updates, and granular permissions.
Project-URL: Homepage, https://github.com/justmagici/capebase
Project-URL: Bug-Tracker, https://github.com/justmagici/capebase/issues
License: MIT License
License-File: LICENSE
Keywords: api-generator,async,authentication,crud,database,fastapi,mysql,permissions,postgresql,pydantic,real-time,sqlalchemy,sqlite,sqlmodel,sse,websockets
Classifier: Development Status :: 3 - Alpha
Classifier: Intended Audience :: Developers
Classifier: License :: OSI Approved :: MIT License
Classifier: Programming Language :: Python :: 3
Classifier: Programming Language :: Python :: 3.10
Classifier: Programming Language :: Python :: 3.11
Classifier: Programming Language :: Python :: 3.12
Classifier: Programming Language :: Python :: 3.13
Classifier: Topic :: Software Development :: Libraries
Classifier: Typing :: Typed
Requires-Python: >=3.10
Requires-Dist: aiosqlite>=0.20.0
Requires-Dist: casbin>=1.37.0
Requires-Dist: fastapi-users>=14.0.1
Requires-Dist: fastapi>=0.115.6
Requires-Dist: greenlet>=3.1.1
Requires-Dist: hatch>=1.14.0
Requires-Dist: httpx-sse>=0.4.0
Requires-Dist: pycasbin>=1.36.3
Requires-Dist: pydantic>=2.10.4
Requires-Dist: sqlmodel>=0.0.22
Requires-Dist: sse-starlette>=2.2.1
